django_pudb.py
django_pudb3-0.2.0.dist-info/LICENSE
django_pudb3-0.2.0.dist-info/METADATA
django_pudb3-0.2.0.dist-info/WHEEL
django_pudb3-0.2.0.dist-info/top_level.txt
django_pudb3-0.2.0.dist-info/RECORD
